fingertip/__init__.py
fingertip/exec.py
fingertip/expiration.py
fingertip/machine.py
fingertip/main.py
fingertip/plugins/ansible.py
fingertip/plugins/backend/podman_criu.py
fingertip/plugins/backend/qemu.py
fingertip/plugins/cleanup.py
fingertip/plugins/console.py
fingertip/plugins/exec.py
fingertip/plugins/filesystem.py
fingertip/plugins/no_op.py
fingertip/plugins/os/alpine.py
fingertip/plugins/os/centos_stream.ks
fingertip/plugins/os/centos_stream.py
fingertip/plugins/os/cloud_init.py
fingertip/plugins/os/common/red_hat_based.py
fingertip/plugins/os/fedora.py
fingertip/plugins/saviour.py
fingertip/plugins/script/__init__.py
fingertip/plugins/script/_run_and_test.py
fingertip/plugins/script/debug.py
fingertip/plugins/self_test/exec.py
fingertip/plugins/self_test/greeting.py
fingertip/plugins/self_test/hostname.py
fingertip/plugins/self_test/prompts.py
fingertip/plugins/self_test/script.py
fingertip/plugins/self_test/ssh_terminate.py
fingertip/plugins/self_test/subshell.py
fingertip/plugins/self_test/wait_for_it.py
fingertip/plugins/software/fingertip.py
fingertip/plugins/ssh.py
fingertip/plugins/transient.py
fingertip/plugins/unseal.py
fingertip/step_loader.py
fingertip/time_desync.py
fingertip/util/cleanup_job.py
fingertip/util/free_port.py
fingertip/util/git_cache.py
fingertip/util/hooks.py
fingertip/util/http_cache.py
fingertip/util/lock.py
fingertip/util/log.py
fingertip/util/optional_pretty_backtraces.py
fingertip/util/path.py
fingertip/util/reflink.py
fingertip/util/repeatedly.py
fingertip/util/temp.py
fingertip/util/units.py
fingertip/util/weak_hash.py
kickstart_templates/fedora32
kickstart_templates/fedora33
kickstart_templates/fedora34
kickstart_templates/fedora35
kickstart_templates/fedora36
ssh_key/fingertip
ssh_key/fingertip.paramiko
ssh_key/fingertip.pub
fingertip-0.3.7.dist-info/entry_points.txt
fingertip-0.3.7.dist-info/WHEEL
fingertip-0.3.7.dist-info/METADATA
fingertip-0.3.7.dist-info/RECORD
